HISTORY.txt
MANIFEST.in
README.rst
setup.py
csnotifier/__init__.py
csnotifier/admin.py
csnotifier/models.py
csnotifier/notifications.py
csnotifier.egg-info/PKG-INFO
csnotifier.egg-info/SOURCES.txt
csnotifier.egg-info/dependency_links.txt
csnotifier.egg-info/entry_points.txt
csnotifier.egg-info/not-zip-safe
csnotifier.egg-info/requires.txt
csnotifier.egg-info/top_level.txt
csnotifier/migrations/0001_initial.py
csnotifier/migrations/0002_auto_20151126_0834.py
csnotifier/migrations/0003_notification_desc.py
csnotifier/migrations/0004_auto_20161212_1351.py
csnotifier/migrations/0005_device_user.py
csnotifier/migrations/0006_auto_20170328_0830.py
csnotifier/migrations/0007_auto_20180518_1551.py
csnotifier/migrations/__init__.py