Metadata-Version: 1.0
Name: csnotifier
Version: 0.14
Summary: A product to send notifications to Pushwosh or Firebase
Home-page: https://codesyntax.com
Author: CodeSyntax
Author-email: info@codesyntax.com
License: GPL2
Platform: UNKNOWN
